pythclient/__init__.py
pythclient/config.py
pythclient/exceptions.py
pythclient/hermes.py
pythclient/market_schedule.py
pythclient/price_feeds.py
pythclient/pythaccounts.py
pythclient/pythclient.py
pythclient/ratelimit.py
pythclient/solana.py
pythclient/utils.py
pythclient-0.2.0.dist-info/LICENSE
pythclient-0.2.0.dist-info/METADATA
pythclient-0.2.0.dist-info/WHEEL
pythclient-0.2.0.dist-info/top_level.txt
pythclient-0.2.0.dist-info/RECORD
