Metadata-Version: 2.1
Name: pythclient
Version: 0.2.0
Summary: A library to retrieve Pyth account structures off the Solana blockchain.
Home-page: https://github.com/pyth-network/pyth-client-py
Author: Pyth Developers
Author-email: contact@pyth.network
Project-URL: Bug Tracker, https://github.com/pyth-network/pyth-client-py/issues
Classifier: Programming Language :: Python :: 3
Classifier: License :: OSI Approved :: Apache Software License
Classifier: Operating System :: OS Independent
Requires-Python: >=3.9.0
License-File: LICENSE
Requires-Dist: aiodns
Requires-Dist: aiohttp>=3.7.4
Requires-Dist: backoff
Requires-Dist: base58
Requires-Dist: flake8
Requires-Dist: loguru
Requires-Dist: typing-extensions
Requires-Dist: pytz
Requires-Dist: pycryptodome
Requires-Dist: httpx
Requires-Dist: websockets
Provides-Extra: testing
Requires-Dist: aiodns; extra == "testing"
Requires-Dist: aiohttp>=3.7.4; extra == "testing"
Requires-Dist: backoff; extra == "testing"
Requires-Dist: base58; extra == "testing"
Requires-Dist: flake8; extra == "testing"
Requires-Dist: loguru; extra == "testing"
Requires-Dist: typing-extensions; extra == "testing"
Requires-Dist: pytz; extra == "testing"
Requires-Dist: pycryptodome; extra == "testing"
Requires-Dist: httpx; extra == "testing"
Requires-Dist: websockets; extra == "testing"
Requires-Dist: mock; extra == "testing"
Requires-Dist: pytest; extra == "testing"
Requires-Dist: pytest-cov; extra == "testing"
Requires-Dist: pytest-socket; extra == "testing"
Requires-Dist: pytest-mock; extra == "testing"
Requires-Dist: pytest-asyncio; extra == "testing"
